e2clab/__init__.py
e2clab/cli.py
e2clab/config.py
e2clab/errors.py
e2clab/experiment.py
e2clab/infra.py
e2clab/log.py
e2clab/network.py
e2clab/objs.py
e2clab/probe.py
e2clab/ssh.py
e2clab/tasks.py
e2clab/utils.py
e2clab/workflow.py
e2clab/constants/__init__.py
e2clab/constants/default.py
e2clab/constants/layers_services.py
e2clab/constants/network.py
e2clab/constants/workflow.py
e2clab/grouping/__init__.py
e2clab/grouping/grouping.py
e2clab/grouping/utils.py
e2clab/managers/__init__.py
e2clab/managers/manager.py
e2clab/managers/monitoring.py
e2clab/managers/monitoring_iot.py
e2clab/managers/monitoring_kwollect.py
e2clab/managers/provenance.py
e2clab/optimizer/Optimizer.py
e2clab/optimizer/__init__.py
e2clab/providers/__init__.py
e2clab/providers/errors.py
e2clab/providers/provider.py
e2clab/providers/utils.py
e2clab/providers/plugins/Chameleoncloud.py
e2clab/providers/plugins/Chameleonedge.py
e2clab/providers/plugins/G5k.py
e2clab/providers/plugins/Iotlab.py
e2clab/providers/plugins/__init__.py
e2clab/schemas/__init__.py
e2clab/schemas/layers_services_schema.py
e2clab/schemas/network_schema.py
e2clab/schemas/utils.py
e2clab/schemas/workflow_env_schema.py
e2clab/schemas/workflow_schema.py
e2clab/services/__init__.py
e2clab/services/constants.py
e2clab/services/errors.py
e2clab/services/service.py
e2clab/services/utils.py
e2clab/services/flowcept/flowcept_service/__init__.py
e2clab/services/flowcept/flowcept_service/flowcept.py
e2clab/services/plugins/Default.py
e2clab/services/plugins/__init__.py
e2clab/services/provenance/__init__.py
e2clab/services/provenance/client_mqttsn_v6.py
e2clab/services/provenance/dataflow-specification.py
e2clab/services/provenance/provenance.py
e2clab/services/provenance/translator.py
e2clab-3.6.0.dist-info/licenses/LICENSE.txt
e2clab-3.6.0.dist-info/METADATA
e2clab-3.6.0.dist-info/WHEEL
e2clab-3.6.0.dist-info/entry_points.txt
e2clab-3.6.0.dist-info/top_level.txt
e2clab-3.6.0.dist-info/RECORD
