Metadata-Version: 2.4
Name: e2clab
Version: 3.6.0
Summary: Your Edge-to-Cloud laboratory
Author-email: Daniel Rosendo <daniel.rosendo@inria.fr>
Maintainer-email: Thomas Badts <thomas.badts@inria.fr>
License:                     GNU GENERAL PUBLIC LICENSE
Project-URL: Homepage, https://e2clab.gitlabpages.inria.fr/e2clab/
Project-URL: Documentation, https://e2clab.gitlabpages.inria.fr/e2clab/
Project-URL: Repository, https://gitlab.inria.fr/E2Clab/e2clab
Keywords: methodology,reproducibility,optimization,edge,cloud,provenance,Grid5000,Chameleon,FIT IoT LAB
Classifier:  Development Status :: 4 - Beta
Classifier: Intended Audience :: System Administrators
Classifier: Intended Audience :: Science/Research
Classifier: License :: OSI Approved :: GNU General Public License v3 (GPLv3)
Classifier: Operating System :: POSIX :: Linux
Classifier: Programming Language :: Python
Classifier: Programming Language :: Python :: 3.9
Classifier: Programming Language :: Python :: 3.10
Classifier: Programming Language :: Python :: 3.11
Requires-Python: <3.12,>=3.9
License-File: LICENSE.txt
Requires-Dist: enoslib[chameleon,iotlab]<11,>=10.1
Requires-Dist: click>=8.1.0
Requires-Dist: jsonschema<5,>=3.2.0
Requires-Dist: parallel-ssh<=2.5.4,>=2.3.2
Requires-Dist: questionary>2.0.0
Requires-Dist: python-dotenv
Provides-Extra: dev
Requires-Dist: tox; extra == "dev"
Requires-Dist: pre-commit; extra == "dev"
Requires-Dist: pytest; extra == "dev"
Requires-Dist: pytest-cov; extra == "dev"
Requires-Dist: ruff; extra == "dev"
Provides-Extra: docs
Requires-Dist: sphinx; extra == "docs"
Requires-Dist: sphinx_rtd_theme; extra == "docs"
Requires-Dist: sphinx-jsonschema; extra == "docs"
Requires-Dist: sphinx-design; extra == "docs"
Requires-Dist: sphinx-click; extra == "docs"
Requires-Dist: sphinx-copybutton; extra == "docs"
Requires-Dist: sphinx-tabs; extra == "docs"
Provides-Extra: opt
Requires-Dist: ray[tune]; extra == "opt"
Dynamic: license-file
